pymergecap/__init__.py
pymergecap/__main__.py
pymergecap/config.ini
pymergecap/main.py
pymergepcap-0.1.2.dist-info/METADATA
pymergepcap-0.1.2.dist-info/WHEEL
pymergepcap-0.1.2.dist-info/entry_points.txt
pymergepcap-0.1.2.dist-info/top_level.txt
pymergepcap-0.1.2.dist-info/RECORD
