Metadata-Version: 2.4
Name: pymergepcap
Version: 0.1.2
Summary: A modern Python GUI tool to generate mergecap commands for merging multiple PCAP or CAP files using Wireshark's mergecap.exe. Features an intuitive interface, flexible configuration, and safe command generation for Windows users.
Project-URL: Repository, https://github.com/fxyzbtc/pymergepcap
Requires-Python: >=3.12
Requires-Dist: freesimplegui>=5.2.0.post1
Requires-Dist: loguru>=0.7.3
Requires-Dist: typer>=0.15.2
